PlayReleaseApi/PlayReleaseApi.py
PlayReleaseApi/__init__.py
PlayReleaseApi-0.0.4.dist-info/LICENSE
PlayReleaseApi-0.0.4.dist-info/METADATA
PlayReleaseApi-0.0.4.dist-info/WHEEL
PlayReleaseApi-0.0.4.dist-info/top_level.txt
PlayReleaseApi-0.0.4.dist-info/RECORD
