Metadata-Version: 2.1
Name: PlayReleaseApi
Version: 0.0.4
Summary: Release Api script for github and Google Play Console
Home-page: https://github.com/mahee96/PlayReleaseApi
Author: mahee96
Author-email: developer.mahee96@gmail.com
License: MIT
Download-URL: https://github.com/mahee96/PlayReleaseApi/releases/download/v0.0.4/PlayReleaseApi.zip
Keywords: Play,GooglePlay,Console,Play Console,python script,Github,Release Api,REST Api,CI,CD,CICD,Continuous Integration
Platform: UNKNOWN
Requires-Dist: requests
